clem/__init__.py
clem/models.py
clem-0.1.0.dist-info/LICENSE
clem-0.1.0.dist-info/METADATA
clem-0.1.0.dist-info/WHEEL
clem-0.1.0.dist-info/top_level.txt
clem-0.1.0.dist-info/RECORD
