Metadata-Version: 2.1
Name: clem
Version: 0.1.0
Summary: Simple and lightweight text variation/formatting language written in pure Python.
Home-page: https://github.com/jakeledoux/clem
Author: Jake Ledoux
Author-email: contactjakeledoux@gmail.com
License: GNU General Public License v2.0
Platform: UNKNOWN
